{
	"info": {
		"_postman_id": "b0f645c0-eee3-419b-9053-e240d348e8e8",
		"name": "Provincia",
		"schema": "https://schema.getpostman.com/json/collection/v2.1.0/collection.json",
		"_exporter_id": "44648620"
	},
	"item": [
		{
			"name": "GET PROVINCIA ID",
			"protocolProfileBehavior": {
				"disableBodyPruning": true
			},
			"request": {
				"method": "GET",
				"header": [],
				"body": {
					"mode": "raw",
					"raw": "{\r\n  \"nombreProvincia\": \"Test_post\"\r\n}"
				},
				"url": {
					"raw": "http://localhost:8090/provincias/10",
					"protocol": "http",
					"host": [
						"localhost"
					],
					"port": "8090",
					"path": [
						"provincias",
						"10"
					]
				}
			},
			"response": []
		},
		{
			"name": "GET ALL PROVINCIAS",
			"protocolProfileBehavior": {
				"disableBodyPruning": true
			},
			"request": {
				"method": "GET",
				"header": [],
				"body": {
					"mode": "raw",
					"raw": "{\r\n  \"nombreProvincia\": \"Test_post\"\r\n}"
				},
				"url": {
					"raw": "http://localhost:8090/provincias",
					"protocol": "http",
					"host": [
						"localhost"
					],
					"port": "8090",
					"path": [
						"provincias"
					]
				}
			},
			"response": []
		},
		{
			"name": "POST PROVINCIA",
			"request": {
				"method": "POST",
				"header": [],
				"body": {
					"mode": "raw",
					"raw": "{\r\n  \"nombreProvincia\": \"Test_posts_video\",\r\n  \"idRegion\": 9\r\n}",
					"options": {
						"raw": {
							"language": "json"
						}
					}
				},
				"url": {
					"raw": "http://localhost:8090/provincias",
					"protocol": "http",
					"host": [
						"localhost"
					],
					"port": "8090",
					"path": [
						"provincias"
					]
				}
			},
			"response": []
		},
		{
			"name": "PUT PROVINCIA",
			"request": {
				"method": "PUT",
				"header": [],
				"body": {
					"mode": "raw",
					"raw": "{\r\n        \"nombreProvincia\": \"Test_put\",\r\n        \"idRegion\": 9\r\n}",
					"options": {
						"raw": {
							"language": "json"
						}
					}
				},
				"url": {
					"raw": "http://localhost:8090/provincias/10",
					"protocol": "http",
					"host": [
						"localhost"
					],
					"port": "8090",
					"path": [
						"provincias",
						"10"
					]
				}
			},
			"response": []
		},
		{
			"name": "DELETE PROVINCIA",
			"request": {
				"method": "DELETE",
				"header": [],
				"body": {
					"mode": "raw",
					"raw": "{\r\n  \"nombreProvincia\": \"Test_post\"\r\n}"
				},
				"url": {
					"raw": "http://localhost:8090/provincias/10",
					"protocol": "http",
					"host": [
						"localhost"
					],
					"port": "8090",
					"path": [
						"provincias",
						"10"
					]
				}
			},
			"response": []
		}
	]
}